mcp_bonusly/__init__.py
mcp_bonusly/client.py
mcp_bonusly/exceptions.py
mcp_bonusly/models.py
mcp_bonusly/server.py
mseep_mcp_bonusly-1.1.2.dist-info/licenses/LICENSE
mseep_mcp_bonusly-1.1.2.dist-info/METADATA
mseep_mcp_bonusly-1.1.2.dist-info/WHEEL
mseep_mcp_bonusly-1.1.2.dist-info/entry_points.txt
mseep_mcp_bonusly-1.1.2.dist-info/top_level.txt
mseep_mcp_bonusly-1.1.2.dist-info/RECORD
